README.md
setup.py
marshmallow_pyspark/__init__.py
marshmallow_pyspark/constants.py
marshmallow_pyspark/converters.py
marshmallow_pyspark/fields.py
marshmallow_pyspark/schema.py
marshmallow_pyspark/version.py
marshmallow_pyspark.egg-info/PKG-INFO
marshmallow_pyspark.egg-info/SOURCES.txt
marshmallow_pyspark.egg-info/dependency_links.txt
marshmallow_pyspark.egg-info/requires.txt
marshmallow_pyspark.egg-info/top_level.txt