Metadata-Version: 2.1
Name: marshmallow-pyspark
Version: 0.2.4
Summary: PySpark data serializer
Home-page: https://github.com/ketgo/marshmallow-pyspark
Author: Ketan Goyal
Author-email: ketangoyal1988@gmail.com
License: Apache 2.0 license
Keywords: pyspark serializer marshmallow data-pipeline data-quality
Platform: UNKNOWN
Classifier: Intended Audience :: Developers
Classifier: License :: OSI Approved :: Apache Software License
Classifier: Operating System :: OS Independent
Classifier: Topic :: System :: Systems Administration
Classifier: Topic :: Software Development
Classifier: Topic :: Utilities
Classifier: Natural Language :: English
Classifier: Programming Language :: Python
Classifier: Programming Language :: Python :: 3.5
Classifier: Programming Language :: Python :: 3.6
Classifier: Programming Language :: Python :: 3.7
Classifier: Programming Language :: Python :: Implementation :: PyPy
Requires-Python: >=3.4
Provides-Extra: dev
